bam_filter/__init__.py
bam_filter/__main__.py
bam_filter/_version.py
bam_filter/entropy.py
bam_filter/filter.py
bam_filter/lca.py
bam_filter/reassign.py
bam_filter/sam_utils.py
bam_filter/utils.py
bam_filter-2.1.0.dist-info/licenses/LICENSE
bam_filter-2.1.0.dist-info/METADATA
bam_filter-2.1.0.dist-info/WHEEL
bam_filter-2.1.0.dist-info/entry_points.txt
bam_filter-2.1.0.dist-info/top_level.txt
bam_filter-2.1.0.dist-info/RECORD
