Metadata-Version: 2.4
Name: bam-filter
Version: 2.1.0
Summary: A simple tool to filter references from a BAM file using different filter types
Home-page: https://github.com/genomewalker/bam-filter
Author: Antonio Fernandez-Guerra
Author-email: antonio@metagenomics.eu
License: GNUv3
Keywords: bam-filter
Classifier: Programming Language :: Python :: 3.7
Classifier: Programming Language :: Python :: 3.8
Classifier: Programming Language :: Python :: 3.9
License-File: LICENSE
Requires-Dist: Cython>=0.29.24
Requires-Dist: pandas>=1.3.3
Requires-Dist: scipy>=1.9.0
Requires-Dist: tqdm>=4.64.1
Requires-Dist: pysam>=0.17.0
Requires-Dist: numpy>1.24
Requires-Dist: pyrle>=0.0.31
Requires-Dist: sorted-nearest>=0.0.38
Requires-Dist: pyranges>=0.0.118
Requires-Dist: kneed>=0.8.1
Requires-Dist: matplotlib>=3.6.0
Requires-Dist: taxopy>=0.12.0
Requires-Dist: python-datatable>=1.1.3
Requires-Dist: networkx>=3.2.1
Requires-Dist: psutil>=5.9.8
Dynamic: author
Dynamic: author-email
Dynamic: classifier
Dynamic: home-page
Dynamic: keywords
Dynamic: license
Dynamic: license-file
Dynamic: requires-dist
Dynamic: summary
